darkyaml
